MANIFEST.in
README.rst
setup.py
sve_common_tools/Sve_QualiITF.py
sve_common_tools/Sve_SSHManager.py
sve_common_tools/Sve_SingletonBuffer.py
sve_common_tools/Sve_file_utils.py
sve_common_tools/Sve_testing_helper.py
sve_common_tools/__init__.py
sve_common_tools.egg-info/PKG-INFO
sve_common_tools.egg-info/SOURCES.txt
sve_common_tools.egg-info/dependency_links.txt
sve_common_tools.egg-info/not-zip-safe
sve_common_tools.egg-info/requires.txt
sve_common_tools.egg-info/top_level.txt