Metadata-Version: 1.0
Name: sve-common-tools
Version: 0.1.7.9
Summary: Utility pack per progetti sve
Home-page: https://pypi.python.org/pypi/sve_common_tools
Author: Riccardo Russo
Author-email: riccardo.russo79@gmail.com
License: MIT
Platform: UNKNOWN
